{"type": "Feature", "id": 12523315, "geometry": {"type": "Point", "coordinates": [-63.099998, 18.0667]}, "properties": {"woe:id": 12523315, "woe:parent_id": 80765, "woe:name": "Marigot Seaplane Base", "woe:placetype": 14, "woe:placetype_name": "Airport", "woe:lang": "ENG", "iso:country": "MF", "meta:provider": ["geoplanet:7.3.1", "geoplanet:7.3.2", "geoplanet:7.4.0", "geoplanet:7.4.1", "geoplanet:7.5.1", "geoplanet:7.5.2", "geoplanet:7.6.0", "geoplanet:7.8.1", "geoplanet:7.9.0", "geoplanet:7.10.0", "geoplanet:8.0.0", "woeplanet:8.0.0"], "meta:indexed": "2020-08-20T20:25:57.555951", "woe:alias_ENG_V": ["Marigot Seaplane", "MSB", "MSB Airport"], "meta:updated": "2020-10-14T11:46:05.939420", "woe:hierarchy": {"continent": 24865672, "country": 56042305, "town": 0, "planet": 1, "county": 0, "suburb": 0, "state": 0, "region": 0, "localadmin": 0}, "woe:timezone_id": 28350760, "woe:hash": "de5nu0gypkzr", "woe:centroid": [-63.099998, 18.0667], "geom:latitude": 18.0667, "geom:longitude": -63.099998, "geom:hash": "de5nu0gypkzr", "woe:latitude": 18.0667, "geom:centroid": [-63.099998, 18.0667], "woe:longitude": -63.099998, "woe:repo": "woeplanet-airport-mf", "geom:area": 0.0, "woe:scale": 19}}